cluster/__init__.py
cluster/grid_search.py
cluster/hp_optimization.py
cluster_utils/__init__.py
cluster_utils/grid_search.py
cluster_utils/hp_optimization.py
cluster_utils/parallel_executor.py
cluster_utils/base/__init__.py
cluster_utils/base/communication.py
cluster_utils/base/constants.py
cluster_utils/base/settings.py
cluster_utils/base/utils.py
cluster_utils/client/__init__.py
cluster_utils/client/server_communication.py
cluster_utils/client/submission_state.py
cluster_utils/scripts/__init__.py
cluster_utils/scripts/generate_report.py
cluster_utils/scripts/plot_job_timeline.py
cluster_utils/server/__init__.py
cluster_utils/server/cluster_system.py
cluster_utils/server/communication_server.py
cluster_utils/server/condor_cluster_system.py
cluster_utils/server/data_analysis.py
cluster_utils/server/distributions.py
cluster_utils/server/dummy_cluster_system.py
cluster_utils/server/git_utils.py
cluster_utils/server/job.py
cluster_utils/server/job_manager.py
cluster_utils/server/latex_utils.py
cluster_utils/server/optimizers.py
cluster_utils/server/progress_bars.py
cluster_utils/server/report.py
cluster_utils/server/settings.py
cluster_utils/server/slurm_cluster_system.py
cluster_utils/server/user_interaction.py
cluster_utils/server/utils.py
cluster_utils-3.0.0.dist-info/LICENSE
cluster_utils-3.0.0.dist-info/METADATA
cluster_utils-3.0.0.dist-info/WHEEL
cluster_utils-3.0.0.dist-info/entry_points.txt
cluster_utils-3.0.0.dist-info/top_level.txt
cluster_utils-3.0.0.dist-info/RECORD
