Metadata-Version: 2.1
Name: cluster-utils
Version: 3.0.0
Summary: A tool for easily running hyperparameter optimization or grid search on Slurm or HTCondor clusters.  It takes care of submitting and monitoring the jobs as well as aggregating the results.
Author: Dominik Zietlow, Sebastian Blaes, Georg Martius, Marin Vlastelica, Maximilian Seitzer, Pierre Schuhmacher, Felix Kloss
Author-email: Michal Rolinek <michalrolinek@gmail.com>
Maintainer-email: georg.martius@uni-tuebingen.de
License: MIT License
Project-URL: Documentation, https://martius-lab.github.io/cluster_utils
Project-URL: Repository, https://github.com/martius-lab/cluster_utils
Project-URL: Issues, https://github.com/martius-lab/cluster_utils/issues
Classifier: Development Status :: 5 - Production/Stable
Classifier: License :: OSI Approved :: MIT License
Classifier: Programming Language :: Python :: 3
Requires-Python: >=3.8
License-File: LICENSE
Requires-Dist: al-smart-settings
Provides-Extra: all
Requires-Dist: cluster-utils[runner] ; extra == 'all'
Requires-Dist: cluster-utils[nevergrad] ; extra == 'all'
Requires-Dist: cluster-utils[report] ; extra == 'all'
Provides-Extra: all-dev
Requires-Dist: cluster-utils[all] ; extra == 'all-dev'
Requires-Dist: cluster-utils[dev] ; extra == 'all-dev'
Requires-Dist: cluster-utils[docs] ; extra == 'all-dev'
Requires-Dist: cluster-utils[mypy] ; extra == 'all-dev'
Provides-Extra: dev
Requires-Dist: absolufy-imports ; extra == 'dev'
Requires-Dist: cluster-utils[lint] ; extra == 'dev'
Requires-Dist: cluster-utils[test] ; extra == 'dev'
Requires-Dist: nox >=2022.8.7 ; extra == 'dev'
Requires-Dist: pre-commit ; extra == 'dev'
Provides-Extra: docs
Requires-Dist: myst-parser ; extra == 'docs'
Requires-Dist: sphinx ; extra == 'docs'
Requires-Dist: sphinx-immaterial ; extra == 'docs'
Provides-Extra: lint
Requires-Dist: black ==24.4.2 ; extra == 'lint'
Requires-Dist: ruff ==0.5.0 ; extra == 'lint'
Provides-Extra: mypy
Requires-Dist: cluster-utils[all] ; extra == 'mypy'
Requires-Dist: mypy ==1.10.1 ; extra == 'mypy'
Requires-Dist: pandas-stubs ; extra == 'mypy'
Requires-Dist: tomli-w ; extra == 'mypy'
Requires-Dist: types-colorama ; extra == 'mypy'
Requires-Dist: types-tqdm ; extra == 'mypy'
Requires-Dist: types-PyYaml ; extra == 'mypy'
Provides-Extra: nevergrad
Requires-Dist: nevergrad ; extra == 'nevergrad'
Provides-Extra: report
Requires-Dist: matplotlib ; extra == 'report'
Requires-Dist: scikit-learn ; extra == 'report'
Requires-Dist: seaborn >=0.11.0 ; extra == 'report'
Provides-Extra: runner
Requires-Dist: colorama ; extra == 'runner'
Requires-Dist: gitpython >=3.0.5 ; extra == 'runner'
Requires-Dist: numpy <2 ; extra == 'runner'
Requires-Dist: pandas[output_formatting] >=2.0.3 ; extra == 'runner'
Requires-Dist: scipy ; extra == 'runner'
Requires-Dist: tqdm ; extra == 'runner'
Provides-Extra: test
Requires-Dist: pytest ==8.2.2 ; extra == 'test'
Requires-Dist: tomli-w ; extra == 'test'
